ansible_vars/__init__.py
ansible_vars/cli.py
ansible_vars/constants.py
ansible_vars/errors.py
ansible_vars/py.typed
ansible_vars/util.py
ansible_vars/vault.py
ansible_vars/vault_crypt.py
ansible_vars/ansible_plugins/action/vault.py
ansible_vars/ansible_plugins/modules/vault.py
ansible_vars-1.0.24.dist-info/METADATA
ansible_vars-1.0.24.dist-info/WHEEL
ansible_vars-1.0.24.dist-info/entry_points.txt
ansible_vars-1.0.24.dist-info/licenses/LICENSE
ansible_vars-1.0.24.dist-info/RECORD
