Metadata-Version: 2.4
Name: ansible-vars
Version: 1.0.24
Summary: Manage vaults and variable files for Ansible
Project-URL: Homepage, https://github.com/xorwow/ansible-vars
Project-URL: Issues, https://github.com/xorwow/ansible-vars/issues
Author-email: xorwow <pip@xorwow.de>
License-File: LICENSE
Classifier: License :: OSI Approved :: MIT License
Classifier: Operating System :: OS Independent
Classifier: Programming Language :: Python :: 3
Requires-Python: >=3.9
Requires-Dist: ansible
Requires-Dist: argcomplete
Requires-Dist: pygments
Requires-Dist: pyyaml
Requires-Dist: ruamel-yaml
Requires-Dist: ruamel-yaml-jinja2
Requires-Dist: termcolor
Requires-Dist: watchdog
